pywebapp3/__init__.py
pywebapp3-0.1.3.dist-info/METADATA
pywebapp3-0.1.3.dist-info/WHEEL
pywebapp3-0.1.3.dist-info/top_level.txt
pywebapp3-0.1.3.dist-info/RECORD
