Metadata-Version: 2.4
Name: PyWebApp3
Version: 0.1.3
Summary: PyWebApp3 is a Python-based web framework that allows you to build responsive, modern web applications using only Python code. No HTML, CSS, or JavaScript knowledge required!
Author: Alex Austin
Author-email: Alex Austin <benmap40@gmail.com>
License: MIT
Requires-Python: >=3.7
Dynamic: author
Dynamic: requires-python
